LICENSE
MANIFEST.in
README.rst
ez_setup.py
setup.cfg
setup.py
hh_elastic2_doc_manager.egg-info/PKG-INFO
hh_elastic2_doc_manager.egg-info/SOURCES.txt
hh_elastic2_doc_manager.egg-info/dependency_links.txt
hh_elastic2_doc_manager.egg-info/requires.txt
hh_elastic2_doc_manager.egg-info/top_level.txt
mongo_connector/__init__.py
mongo_connector/doc_managers/__init__.py
mongo_connector/doc_managers/formatters_proxy.py
mongo_connector/doc_managers/hh_elastic2_doc_manager.py