Metadata-Version: 1.1
Name: hh-elastic2-doc-manager
Version: 0.1.0
Summary: Elastic2 plugin for mongo-connector
Home-page: https://github.com/mongodb-labs/elastic2-doc-manager
Author: mongodb
Author-email: 757441448@qq.com
License: Apache License, Version 2.0
Keywords: mongo-connector,mongodb,elastic,elasticsearch
Platform: any
Classifier: Development Status :: 4 - Beta
Classifier: Intended Audience :: Developers
Classifier: License :: OSI Approved :: Apache Software License
Classifier: Programming Language :: Python :: 2.6
Classifier: Programming Language :: Python :: 2.7
Classifier: Programming Language :: Python :: 3.3
Classifier: Programming Language :: Python :: 3.4
Classifier: Programming Language :: Python :: 3.5
Classifier: Topic :: Database
Classifier: Topic :: Software Development :: Libraries :: Python Modules
Classifier: Operating System :: Unix
Classifier: Operating System :: MacOS :: MacOS X
Classifier: Operating System :: Microsoft :: Windows
Classifier: Operating System :: POSIX
